{
  "generated_at": "2026-07-17T14:41:49+00:00",
  "stats": {
    "crypto_count": 6,
    "stocks_count": 30,
    "scored_count": 17,
    "top_n": 10
  },
  "lists": {
    "combined": [
      {
        "type": "stock",
        "symbol": "NFLX",
        "name": "Netflix",
        "price": 67.92220306396484,
        "change_24h": -8.645320164187446,
        "rsi": 28.901557546858797,
        "dist_from_ma20": -8.001405725699172,
        "volume_ratio": 1.2041004128222226,
        "macd": {
          "macd": -2.343941609405263,
          "signal": -2.3708911159564066,
          "histogram": 0.026949506551143365,
          "crossover": null
        },
        "bollinger": {
          "upper": 78.28611580379143,
          "lower": 69.37310355656012,
          "middle": 73.82960968017578,
          "percent_b": -0.16278452809777988
        },
        "score": 107.6,
        "signals": [
          {
            "kind": "bull",
            "label": "RSI ipervenduto",
            "value": "28.9"
          },
          {
            "kind": "bull",
            "label": "Crollo 24h",
            "value": "-8.65%"
          },
          {
            "kind": "bull",
            "label": "Sotto MA20",
            "value": "-8.0%"
          },
          {
            "kind": "bull",
            "label": "MACD ripresa",
            "value": ""
          },
          {
            "kind": "bull",
            "label": "Sotto BB inf",
            "value": "%B -0.16"
          }
        ]
      },
      {
        "type": "crypto",
        "symbol": "HYPEUSDT",
        "name": "HYPE",
        "price": 60.36,
        "change_24h": -7.974,
        "rsi": 32.621502211008576,
        "dist_from_ma20": -6.422957071764085,
        "volume_ratio": 4.3883113264102285,
        "macd": {
          "macd": -1.6108262697815192,
          "signal": -0.9787704885288695,
          "histogram": -0.6320557812526497,
          "crossover": null
        },
        "bollinger": {
          "upper": 70.22213664813141,
          "lower": 58.783863351868554,
          "middle": 64.50299999999999,
          "percent_b": 0.1377949807027609
        },
        "score": 80.2,
        "signals": [
          {
            "kind": "bull",
            "label": "Crollo 24h",
            "value": "-7.97%"
          },
          {
            "kind": "bull",
            "label": "Sotto MA20",
            "value": "-6.4%"
          },
          {
            "kind": "bull",
            "label": "Volume 4.4x",
            "value": ""
          },
          {
            "kind": "bull",
            "label": "BB inferiore",
            "value": "%B 0.14"
          }
        ]
      },
      {
        "type": "stock",
        "symbol": "AMD",
        "name": "AMD",
        "price": 490.92999267578125,
        "change_24h": -1.9982452423123958,
        "rsi": 45.433790412887696,
        "dist_from_ma20": -7.8545929491679285,
        "volume_ratio": 0.7290770660722825,
        "macd": {
          "macd": 7.2770326137825805,
          "signal": 15.636818128131079,
          "histogram": -8.359785514348498,
          "crossover": null
        },
        "bollinger": {
          "upper": 573.3163652617865,
          "lower": 492.23862741399483,
          "middle": 532.7774963378906,
          "percent_b": -0.01614049396235379
        },
        "score": 65.7,
        "signals": [
          {
            "kind": "bull",
            "label": "Sotto MA20",
            "value": "-7.9%"
          },
          {
            "kind": "bull",
            "label": "Sotto BB inf",
            "value": "%B -0.02"
          }
        ]
      },
      {
        "type": "crypto",
        "symbol": "SOLUSDT",
        "name": "SOL",
        "price": 74.46,
        "change_24h": -2.806,
        "rsi": 33.949861594673735,
        "dist_from_ma20": -2.640576886616685,
        "volume_ratio": 1.261179671604463,
        "macd": {
          "macd": -0.608712078359531,
          "signal": -0.3907271102731697,
          "histogram": -0.2179849680863613,
          "crossover": null
        },
        "bollinger": {
          "upper": 78.71931673357443,
          "lower": 74.23968326642557,
          "middle": 76.4795,
          "percent_b": 0.04918186614822432
        },
        "score": 50.0,
        "signals": [
          {
            "kind": "bull",
            "label": "Sotto BB inf",
            "value": "%B 0.05"
          }
        ]
      },
      {
        "type": "stock",
        "symbol": "SIE.DE",
        "name": "Siemens",
        "price": 263.3500061035156,
        "change_24h": -2.7151849915301605,
        "rsi": 42.69504848456764,
        "dist_from_ma20": -3.533029936101274,
        "volume_ratio": 0.7844351804470906,
        "macd": {
          "macd": -0.1001649868903769,
          "signal": 1.2248059741662825,
          "histogram": -1.3249709610566593,
          "crossover": null
        },
        "bollinger": {
          "upper": 283.37329046893467,
          "lower": 262.61671197247153,
          "middle": 272.9950012207031,
          "percent_b": 0.03532827586054424
        },
        "score": 50.0,
        "signals": [
          {
            "kind": "bull",
            "label": "Sotto BB inf",
            "value": "%B 0.04"
          }
        ]
      },
      {
        "type": "stock",
        "symbol": "ASML.AS",
        "name": "ASML Holding",
        "price": 1526.0,
        "change_24h": -4.5295309877514995,
        "rsi": 47.101532881150824,
        "dist_from_ma20": -3.8413079805804085,
        "volume_ratio": 0.991528365732481,
        "macd": {
          "macd": 9.64320249076377,
          "signal": 23.660353648185072,
          "histogram": -14.017151157421303,
          "crossover": null
        },
        "bollinger": {
          "upper": 1687.591510397021,
          "lower": 1486.3285335482915,
          "middle": 1586.9600219726562,
          "percent_b": 0.1971125890755647
        },
        "score": 38.6,
        "signals": [
          {
            "kind": "bull",
            "label": "Crollo 24h",
            "value": "-4.53%"
          },
          {
            "kind": "bull",
            "label": "BB inferiore",
            "value": "%B 0.20"
          }
        ]
      },
      {
        "type": "crypto",
        "symbol": "ETHUSDT",
        "name": "ETH",
        "price": 1826.42,
        "change_24h": -3.02,
        "rsi": 42.488831618141354,
        "dist_from_ma20": -2.694751546416721,
        "volume_ratio": 0.29481558370183036,
        "macd": {
          "macd": 5.82311006273676,
          "signal": 17.191142411089746,
          "histogram": -11.368032348352987,
          "crossover": null
        },
        "bollinger": {
          "upper": 1945.8751239118585,
          "lower": 1808.1258760881408,
          "middle": 1877.0004999999996,
          "percent_b": 0.13280743235179682
        },
        "score": 34.1,
        "signals": [
          {
            "kind": "bull",
            "label": "Crollo 24h",
            "value": "-3.02%"
          },
          {
            "kind": "bull",
            "label": "BB inferiore",
            "value": "%B 0.13"
          }
        ]
      },
      {
        "type": "crypto",
        "symbol": "BTCUSDT",
        "name": "BTC",
        "price": 63306.74,
        "change_24h": -2.192,
        "rsi": 43.60911049798735,
        "dist_from_ma20": -1.5006597236173835,
        "volume_ratio": 0.49103016419067014,
        "macd": {
          "macd": -93.44057870779943,
          "signal": 96.41558510139126,
          "histogram": -189.8561638091907,
          "crossover": null
        },
        "bollinger": {
          "upper": 65713.06025237369,
          "lower": 62829.404747626286,
          "middle": 64271.232499999984,
          "percent_b": 0.16553130274676303
        },
        "score": 25.0,
        "signals": [
          {
            "kind": "bull",
            "label": "BB inferiore",
            "value": "%B 0.17"
          }
        ]
      },
      {
        "type": "crypto",
        "symbol": "XRPUSDT",
        "name": "XRP",
        "price": 1.0853,
        "change_24h": -2.629,
        "rsi": 43.38579595713791,
        "dist_from_ma20": -1.5399968247488314,
        "volume_ratio": 0.23960915070138472,
        "macd": {
          "macd": -0.002343547613512964,
          "signal": 0.0004051482209406324,
          "histogram": -0.0027486958344535963,
          "crossover": null
        },
        "bollinger": {
          "upper": 1.1291597075490882,
          "lower": 1.075390292450912,
          "middle": 1.1022750000000001,
          "percent_b": 0.18430008083580682
        },
        "score": 25.0,
        "signals": [
          {
            "kind": "bull",
            "label": "BB inferiore",
            "value": "%B 0.18"
          }
        ]
      },
      {
        "type": "stock",
        "symbol": "META",
        "name": "Meta Platforms",
        "price": 635.2191772460938,
        "change_24h": -4.412195165185914,
        "rsi": 53.931170103190844,
        "dist_from_ma20": 5.0445715171726695,
        "volume_ratio": 0.6567315637622408,
        "macd": {
          "macd": 17.78184449649075,
          "signal": 9.924856748611745,
          "histogram": 7.856987747879003,
          "crossover": null
        },
        "bollinger": {
          "upper": 692.5105523601425,
          "lower": 516.9173468097794,
          "middle": 604.7139495849609,
          "percent_b": 0.6737266972575623
        },
        "score": 13.2,
        "signals": [
          {
            "kind": "bull",
            "label": "Crollo 24h",
            "value": "-4.41%"
          }
        ]
      }
    ],
    "crypto": [
      {
        "type": "crypto",
        "symbol": "HYPEUSDT",
        "name": "HYPE",
        "price": 60.36,
        "change_24h": -7.974,
        "rsi": 32.621502211008576,
        "dist_from_ma20": -6.422957071764085,
        "volume_ratio": 4.3883113264102285,
        "macd": {
          "macd": -1.6108262697815192,
          "signal": -0.9787704885288695,
          "histogram": -0.6320557812526497,
          "crossover": null
        },
        "bollinger": {
          "upper": 70.22213664813141,
          "lower": 58.783863351868554,
          "middle": 64.50299999999999,
          "percent_b": 0.1377949807027609
        },
        "score": 80.2,
        "signals": [
          {
            "kind": "bull",
            "label": "Crollo 24h",
            "value": "-7.97%"
          },
          {
            "kind": "bull",
            "label": "Sotto MA20",
            "value": "-6.4%"
          },
          {
            "kind": "bull",
            "label": "Volume 4.4x",
            "value": ""
          },
          {
            "kind": "bull",
            "label": "BB inferiore",
            "value": "%B 0.14"
          }
        ]
      },
      {
        "type": "crypto",
        "symbol": "SOLUSDT",
        "name": "SOL",
        "price": 74.46,
        "change_24h": -2.806,
        "rsi": 33.949861594673735,
        "dist_from_ma20": -2.640576886616685,
        "volume_ratio": 1.261179671604463,
        "macd": {
          "macd": -0.608712078359531,
          "signal": -0.3907271102731697,
          "histogram": -0.2179849680863613,
          "crossover": null
        },
        "bollinger": {
          "upper": 78.71931673357443,
          "lower": 74.23968326642557,
          "middle": 76.4795,
          "percent_b": 0.04918186614822432
        },
        "score": 50.0,
        "signals": [
          {
            "kind": "bull",
            "label": "Sotto BB inf",
            "value": "%B 0.05"
          }
        ]
      },
      {
        "type": "crypto",
        "symbol": "ETHUSDT",
        "name": "ETH",
        "price": 1826.42,
        "change_24h": -3.02,
        "rsi": 42.488831618141354,
        "dist_from_ma20": -2.694751546416721,
        "volume_ratio": 0.29481558370183036,
        "macd": {
          "macd": 5.82311006273676,
          "signal": 17.191142411089746,
          "histogram": -11.368032348352987,
          "crossover": null
        },
        "bollinger": {
          "upper": 1945.8751239118585,
          "lower": 1808.1258760881408,
          "middle": 1877.0004999999996,
          "percent_b": 0.13280743235179682
        },
        "score": 34.1,
        "signals": [
          {
            "kind": "bull",
            "label": "Crollo 24h",
            "value": "-3.02%"
          },
          {
            "kind": "bull",
            "label": "BB inferiore",
            "value": "%B 0.13"
          }
        ]
      },
      {
        "type": "crypto",
        "symbol": "BTCUSDT",
        "name": "BTC",
        "price": 63306.74,
        "change_24h": -2.192,
        "rsi": 43.60911049798735,
        "dist_from_ma20": -1.5006597236173835,
        "volume_ratio": 0.49103016419067014,
        "macd": {
          "macd": -93.44057870779943,
          "signal": 96.41558510139126,
          "histogram": -189.8561638091907,
          "crossover": null
        },
        "bollinger": {
          "upper": 65713.06025237369,
          "lower": 62829.404747626286,
          "middle": 64271.232499999984,
          "percent_b": 0.16553130274676303
        },
        "score": 25.0,
        "signals": [
          {
            "kind": "bull",
            "label": "BB inferiore",
            "value": "%B 0.17"
          }
        ]
      },
      {
        "type": "crypto",
        "symbol": "XRPUSDT",
        "name": "XRP",
        "price": 1.0853,
        "change_24h": -2.629,
        "rsi": 43.38579595713791,
        "dist_from_ma20": -1.5399968247488314,
        "volume_ratio": 0.23960915070138472,
        "macd": {
          "macd": -0.002343547613512964,
          "signal": 0.0004051482209406324,
          "histogram": -0.0027486958344535963,
          "crossover": null
        },
        "bollinger": {
          "upper": 1.1291597075490882,
          "lower": 1.075390292450912,
          "middle": 1.1022750000000001,
          "percent_b": 0.18430008083580682
        },
        "score": 25.0,
        "signals": [
          {
            "kind": "bull",
            "label": "BB inferiore",
            "value": "%B 0.18"
          }
        ]
      }
    ],
    "stocks": [
      {
        "type": "stock",
        "symbol": "NFLX",
        "name": "Netflix",
        "price": 67.92220306396484,
        "change_24h": -8.645320164187446,
        "rsi": 28.901557546858797,
        "dist_from_ma20": -8.001405725699172,
        "volume_ratio": 1.2041004128222226,
        "macd": {
          "macd": -2.343941609405263,
          "signal": -2.3708911159564066,
          "histogram": 0.026949506551143365,
          "crossover": null
        },
        "bollinger": {
          "upper": 78.28611580379143,
          "lower": 69.37310355656012,
          "middle": 73.82960968017578,
          "percent_b": -0.16278452809777988
        },
        "score": 107.6,
        "signals": [
          {
            "kind": "bull",
            "label": "RSI ipervenduto",
            "value": "28.9"
          },
          {
            "kind": "bull",
            "label": "Crollo 24h",
            "value": "-8.65%"
          },
          {
            "kind": "bull",
            "label": "Sotto MA20",
            "value": "-8.0%"
          },
          {
            "kind": "bull",
            "label": "MACD ripresa",
            "value": ""
          },
          {
            "kind": "bull",
            "label": "Sotto BB inf",
            "value": "%B -0.16"
          }
        ]
      },
      {
        "type": "stock",
        "symbol": "AMD",
        "name": "AMD",
        "price": 490.92999267578125,
        "change_24h": -1.9982452423123958,
        "rsi": 45.433790412887696,
        "dist_from_ma20": -7.8545929491679285,
        "volume_ratio": 0.7290770660722825,
        "macd": {
          "macd": 7.2770326137825805,
          "signal": 15.636818128131079,
          "histogram": -8.359785514348498,
          "crossover": null
        },
        "bollinger": {
          "upper": 573.3163652617865,
          "lower": 492.23862741399483,
          "middle": 532.7774963378906,
          "percent_b": -0.01614049396235379
        },
        "score": 65.7,
        "signals": [
          {
            "kind": "bull",
            "label": "Sotto MA20",
            "value": "-7.9%"
          },
          {
            "kind": "bull",
            "label": "Sotto BB inf",
            "value": "%B -0.02"
          }
        ]
      },
      {
        "type": "stock",
        "symbol": "SIE.DE",
        "name": "Siemens",
        "price": 263.3500061035156,
        "change_24h": -2.7151849915301605,
        "rsi": 42.69504848456764,
        "dist_from_ma20": -3.533029936101274,
        "volume_ratio": 0.7844351804470906,
        "macd": {
          "macd": -0.1001649868903769,
          "signal": 1.2248059741662825,
          "histogram": -1.3249709610566593,
          "crossover": null
        },
        "bollinger": {
          "upper": 283.37329046893467,
          "lower": 262.61671197247153,
          "middle": 272.9950012207031,
          "percent_b": 0.03532827586054424
        },
        "score": 50.0,
        "signals": [
          {
            "kind": "bull",
            "label": "Sotto BB inf",
            "value": "%B 0.04"
          }
        ]
      },
      {
        "type": "stock",
        "symbol": "ASML.AS",
        "name": "ASML Holding",
        "price": 1526.0,
        "change_24h": -4.5295309877514995,
        "rsi": 47.101532881150824,
        "dist_from_ma20": -3.8413079805804085,
        "volume_ratio": 0.991528365732481,
        "macd": {
          "macd": 9.64320249076377,
          "signal": 23.660353648185072,
          "histogram": -14.017151157421303,
          "crossover": null
        },
        "bollinger": {
          "upper": 1687.591510397021,
          "lower": 1486.3285335482915,
          "middle": 1586.9600219726562,
          "percent_b": 0.1971125890755647
        },
        "score": 38.6,
        "signals": [
          {
            "kind": "bull",
            "label": "Crollo 24h",
            "value": "-4.53%"
          },
          {
            "kind": "bull",
            "label": "BB inferiore",
            "value": "%B 0.20"
          }
        ]
      },
      {
        "type": "stock",
        "symbol": "META",
        "name": "Meta Platforms",
        "price": 635.2191772460938,
        "change_24h": -4.412195165185914,
        "rsi": 53.931170103190844,
        "dist_from_ma20": 5.0445715171726695,
        "volume_ratio": 0.6567315637622408,
        "macd": {
          "macd": 17.78184449649075,
          "signal": 9.924856748611745,
          "histogram": 7.856987747879003,
          "crossover": null
        },
        "bollinger": {
          "upper": 692.5105523601425,
          "lower": 516.9173468097794,
          "middle": 604.7139495849609,
          "percent_b": 0.6737266972575623
        },
        "score": 13.2,
        "signals": [
          {
            "kind": "bull",
            "label": "Crollo 24h",
            "value": "-4.41%"
          }
        ]
      },
      {
        "type": "stock",
        "symbol": "MSFT",
        "name": "Microsoft",
        "price": 391.9200134277344,
        "change_24h": -2.2887041974793894,
        "rsi": 50.622007317331416,
        "dist_from_ma20": 2.8492744802873893,
        "volume_ratio": 0.6412708177433261,
        "macd": {
          "macd": -1.4062568545909357,
          "signal": -4.6361291507401345,
          "histogram": 3.229872296149199,
          "crossover": null
        },
        "bollinger": {
          "upper": 404.03192908698065,
          "lower": 358.09306480950374,
          "middle": 381.0624969482422,
          "percent_b": 0.7363470810665087
        },
        "score": 12.0,
        "signals": [
          {
            "kind": "bull",
            "label": "MACD ripresa",
            "value": ""
          }
        ]
      },
      {
        "type": "stock",
        "symbol": "DIS",
        "name": "Disney",
        "price": 98.41999816894531,
        "change_24h": -1.2937528105225198,
        "rsi": 49.7231343569091,
        "dist_from_ma20": 0.27110557969799803,
        "volume_ratio": 0.6166623357807357,
        "macd": {
          "macd": -0.7663468147954404,
          "signal": -1.0437376335052297,
          "histogram": 0.2773908187097893,
          "crossover": null
        },
        "bollinger": {
          "upper": 102.66546649070868,
          "lower": 93.6423284616839,
          "middle": 98.15389747619629,
          "percent_b": 0.5294909256505944
        },
        "score": 12.0,
        "signals": [
          {
            "kind": "bull",
            "label": "MACD ripresa",
            "value": ""
          }
        ]
      },
      {
        "type": "stock",
        "symbol": "SAP.DE",
        "name": "SAP SE",
        "price": 138.60000610351562,
        "change_24h": 0.6974765461524604,
        "rsi": 47.268904547779165,
        "dist_from_ma20": 0.8073352102675962,
        "volume_ratio": 0.7458121714360212,
        "macd": {
          "macd": -1.5700458255204524,
          "signal": -1.9647437765083882,
          "histogram": 0.3946979509879358,
          "crossover": null
        },
        "bollinger": {
          "upper": 143.54990781746886,
          "lower": 131.4300940135858,
          "middle": 137.49000091552733,
          "percent_b": 0.5915859934772808
        },
        "score": 12.0,
        "signals": [
          {
            "kind": "bull",
            "label": "MACD ripresa",
            "value": ""
          }
        ]
      },
      {
        "type": "stock",
        "symbol": "ENI.MI",
        "name": "ENI",
        "price": 21.665000915527344,
        "change_24h": 2.6290871109858216,
        "rsi": 53.40882613330008,
        "dist_from_ma20": 3.706190475386157,
        "volume_ratio": 0.7116650909078066,
        "macd": {
          "macd": -0.18302645863924738,
          "signal": -0.36133020598297577,
          "histogram": 0.1783037473437284,
          "crossover": null
        },
        "bollinger": {
          "upper": 21.9135028757075,
          "lower": 19.867996986963398,
          "middle": 20.89074993133545,
          "percent_b": 0.8785132022608199
        },
        "score": 12.0,
        "signals": [
          {
            "kind": "bull",
            "label": "MACD ripresa",
            "value": ""
          }
        ]
      },
      {
        "type": "stock",
        "symbol": "STLAM.MI",
        "name": "Stellantis",
        "price": 5.125,
        "change_24h": -2.380952380952381,
        "rsi": 44.210029891085526,
        "dist_from_ma20": 1.5062546421605765,
        "volume_ratio": 0.7532546148343183,
        "macd": {
          "macd": -0.21392441791190997,
          "signal": -0.2936537302813509,
          "histogram": 0.07972931236944092,
          "crossover": null
        },
        "bollinger": {
          "upper": 5.470593253341459,
          "lower": 4.627306660446383,
          "middle": 5.048949956893921,
          "percent_b": 0.5901829149743656
        },
        "score": 12.0,
        "signals": [
          {
            "kind": "bull",
            "label": "MACD ripresa",
            "value": ""
          }
        ]
      }
    ]
  }
}