{
  "generated_at": "2026-05-14T14:06:34+00:00",
  "stats": {
    "crypto_count": 5,
    "stocks_count": 30,
    "scored_count": 8,
    "top_n": 10
  },
  "lists": {
    "combined": [
      {
        "type": "stock",
        "symbol": "SAP.DE",
        "name": "SAP SE",
        "price": 137.33999633789062,
        "change_24h": 0.7926037535547572,
        "rsi": 39.08689445757973,
        "dist_from_ma20": -5.582983417097749,
        "volume_ratio": 0.6833502929871558,
        "macd": {
          "macd": -2.266407477385883,
          "signal": -1.734515132247088,
          "histogram": -0.5318923451387949,
          "crossover": null
        },
        "bollinger": {
          "upper": 154.13544652896996,
          "lower": 136.78668024104957,
          "middle": 145.46106338500977,
          "percent_b": 0.03189368556001135
        },
        "score": 61.2,
        "signals": [
          {
            "kind": "bull",
            "label": "Sotto MA20",
            "value": "-5.6%"
          },
          {
            "kind": "bull",
            "label": "Sotto BB inf",
            "value": "%B 0.03"
          }
        ]
      },
      {
        "type": "stock",
        "symbol": "PEP",
        "name": "PepsiCo",
        "price": 149.66000366210938,
        "change_24h": 0.26127110503499135,
        "rsi": 39.428170243929436,
        "dist_from_ma20": -3.219754576025874,
        "volume_ratio": 0.70200117686876,
        "macd": {
          "macd": -1.5767517984542394,
          "signal": -0.9661015485406905,
          "histogram": -0.6106502499135489,
          "crossover": null
        },
        "bollinger": {
          "upper": 159.8658893330402,
          "lower": 149.4121105448895,
          "middle": 154.63899993896484,
          "percent_b": 0.023713254531545425
        },
        "score": 50.0,
        "signals": [
          {
            "kind": "bull",
            "label": "Sotto BB inf",
            "value": "%B 0.02"
          }
        ]
      },
      {
        "type": "stock",
        "symbol": "LDO.MI",
        "name": "Leonardo",
        "price": 49.59000015258789,
        "change_24h": -0.5016051349009055,
        "rsi": 33.59006651963915,
        "dist_from_ma20": -7.4705533218447915,
        "volume_ratio": 0.7092834590561571,
        "macd": {
          "macd": -1.8417900376548175,
          "signal": -1.5244701085377994,
          "histogram": -0.3173199291170181,
          "crossover": null
        },
        "bollinger": {
          "upper": 58.56596488247968,
          "lower": 48.621534736050585,
          "middle": 53.593749809265134,
          "percent_b": 0.09738772380889699
        },
        "score": 39.9,
        "signals": [
          {
            "kind": "bull",
            "label": "Sotto MA20",
            "value": "-7.5%"
          },
          {
            "kind": "bull",
            "label": "BB inferiore",
            "value": "%B 0.10"
          }
        ]
      },
      {
        "type": "stock",
        "symbol": "MONC.MI",
        "name": "Moncler",
        "price": 50.81999969482422,
        "change_24h": 0.039370980441040586,
        "rsi": 41.62043655597154,
        "dist_from_ma20": -5.386033932631574,
        "volume_ratio": 0.8347576979234373,
        "macd": {
          "macd": -0.6899663395098514,
          "signal": -0.33660632441770344,
          "histogram": -0.353360015092148,
          "crossover": null
        },
        "bollinger": {
          "upper": 58.15678801371636,
          "lower": 49.26921219990668,
          "middle": 53.71300010681152,
          "percent_b": 0.17448936891293737
        },
        "score": 35.8,
        "signals": [
          {
            "kind": "bull",
            "label": "Sotto MA20",
            "value": "-5.4%"
          },
          {
            "kind": "bull",
            "label": "BB inferiore",
            "value": "%B 0.17"
          }
        ]
      },
      {
        "type": "stock",
        "symbol": "MSFT",
        "name": "Microsoft",
        "price": 403.8900146484375,
        "change_24h": -0.32575129796298685,
        "rsi": 46.81314806717409,
        "dist_from_ma20": -3.1838151816867644,
        "volume_ratio": 0.7194833679477054,
        "macd": {
          "macd": 2.5327926483338956,
          "signal": 5.194466343846221,
          "histogram": -2.6616736955123255,
          "crossover": null
        },
        "bollinger": {
          "upper": 432.93110917334843,
          "lower": 401.41289107079217,
          "middle": 417.1720001220703,
          "percent_b": 0.07859338905470752
        },
        "score": 25.0,
        "signals": [
          {
            "kind": "bull",
            "label": "BB inferiore",
            "value": "%B 0.08"
          }
        ]
      },
      {
        "type": "stock",
        "symbol": "JPM",
        "name": "JPMorgan",
        "price": 302.625,
        "change_24h": 0.7910074937552041,
        "rsi": 46.67445694497381,
        "dist_from_ma20": -2.0532011732578135,
        "volume_ratio": 0.761202812409594,
        "macd": {
          "macd": -0.189901612671747,
          "signal": 1.4447129924603128,
          "histogram": -1.6346146051320598,
          "crossover": null
        },
        "bollinger": {
          "upper": 318.51178985443124,
          "lower": 299.42571014556876,
          "middle": 308.96875,
          "percent_b": 0.16762425302801576
        },
        "score": 25.0,
        "signals": [
          {
            "kind": "bull",
            "label": "BB inferiore",
            "value": "%B 0.17"
          }
        ]
      },
      {
        "type": "stock",
        "symbol": "MA",
        "name": "Mastercard",
        "price": 491.17498779296875,
        "change_24h": 0.10903577542785191,
        "rsi": 43.276365147611244,
        "dist_from_ma20": -2.4791962027723815,
        "volume_ratio": 0.6363016790593797,
        "macd": {
          "macd": -3.5976519518446253,
          "signal": -2.198957337392647,
          "histogram": -1.398694614451978,
          "crossover": null
        },
        "bollinger": {
          "upper": 522.4837990184759,
          "lower": 484.8397025684381,
          "middle": 503.66175079345703,
          "percent_b": 0.16829425652277247
        },
        "score": 25.0,
        "signals": [
          {
            "kind": "bull",
            "label": "BB inferiore",
            "value": "%B 0.17"
          }
        ]
      },
      {
        "type": "stock",
        "symbol": "MC.PA",
        "name": "LVMH",
        "price": 460.04998779296875,
        "change_24h": 1.713464560946972,
        "rsi": 47.64065843578508,
        "dist_from_ma20": -0.8486363689758823,
        "volume_ratio": 0.7259253765815775,
        "macd": {
          "macd": -4.953600815646496,
          "signal": -5.417531137622568,
          "histogram": 0.463930321976072,
          "crossover": null
        },
        "bollinger": {
          "upper": 489.69324922556893,
          "lower": 438.28186063771227,
          "middle": 463.9875549316406,
          "percent_b": 0.42341060518248863
        },
        "score": 12.0,
        "signals": [
          {
            "kind": "bull",
            "label": "MACD ripresa",
            "value": ""
          }
        ]
      }
    ],
    "crypto": [],
    "stocks": [
      {
        "type": "stock",
        "symbol": "SAP.DE",
        "name": "SAP SE",
        "price": 137.33999633789062,
        "change_24h": 0.7926037535547572,
        "rsi": 39.08689445757973,
        "dist_from_ma20": -5.582983417097749,
        "volume_ratio": 0.6833502929871558,
        "macd": {
          "macd": -2.266407477385883,
          "signal": -1.734515132247088,
          "histogram": -0.5318923451387949,
          "crossover": null
        },
        "bollinger": {
          "upper": 154.13544652896996,
          "lower": 136.78668024104957,
          "middle": 145.46106338500977,
          "percent_b": 0.03189368556001135
        },
        "score": 61.2,
        "signals": [
          {
            "kind": "bull",
            "label": "Sotto MA20",
            "value": "-5.6%"
          },
          {
            "kind": "bull",
            "label": "Sotto BB inf",
            "value": "%B 0.03"
          }
        ]
      },
      {
        "type": "stock",
        "symbol": "PEP",
        "name": "PepsiCo",
        "price": 149.66000366210938,
        "change_24h": 0.26127110503499135,
        "rsi": 39.428170243929436,
        "dist_from_ma20": -3.219754576025874,
        "volume_ratio": 0.70200117686876,
        "macd": {
          "macd": -1.5767517984542394,
          "signal": -0.9661015485406905,
          "histogram": -0.6106502499135489,
          "crossover": null
        },
        "bollinger": {
          "upper": 159.8658893330402,
          "lower": 149.4121105448895,
          "middle": 154.63899993896484,
          "percent_b": 0.023713254531545425
        },
        "score": 50.0,
        "signals": [
          {
            "kind": "bull",
            "label": "Sotto BB inf",
            "value": "%B 0.02"
          }
        ]
      },
      {
        "type": "stock",
        "symbol": "LDO.MI",
        "name": "Leonardo",
        "price": 49.59000015258789,
        "change_24h": -0.5016051349009055,
        "rsi": 33.59006651963915,
        "dist_from_ma20": -7.4705533218447915,
        "volume_ratio": 0.7092834590561571,
        "macd": {
          "macd": -1.8417900376548175,
          "signal": -1.5244701085377994,
          "histogram": -0.3173199291170181,
          "crossover": null
        },
        "bollinger": {
          "upper": 58.56596488247968,
          "lower": 48.621534736050585,
          "middle": 53.593749809265134,
          "percent_b": 0.09738772380889699
        },
        "score": 39.9,
        "signals": [
          {
            "kind": "bull",
            "label": "Sotto MA20",
            "value": "-7.5%"
          },
          {
            "kind": "bull",
            "label": "BB inferiore",
            "value": "%B 0.10"
          }
        ]
      },
      {
        "type": "stock",
        "symbol": "MONC.MI",
        "name": "Moncler",
        "price": 50.81999969482422,
        "change_24h": 0.039370980441040586,
        "rsi": 41.62043655597154,
        "dist_from_ma20": -5.386033932631574,
        "volume_ratio": 0.8347576979234373,
        "macd": {
          "macd": -0.6899663395098514,
          "signal": -0.33660632441770344,
          "histogram": -0.353360015092148,
          "crossover": null
        },
        "bollinger": {
          "upper": 58.15678801371636,
          "lower": 49.26921219990668,
          "middle": 53.71300010681152,
          "percent_b": 0.17448936891293737
        },
        "score": 35.8,
        "signals": [
          {
            "kind": "bull",
            "label": "Sotto MA20",
            "value": "-5.4%"
          },
          {
            "kind": "bull",
            "label": "BB inferiore",
            "value": "%B 0.17"
          }
        ]
      },
      {
        "type": "stock",
        "symbol": "MSFT",
        "name": "Microsoft",
        "price": 403.8900146484375,
        "change_24h": -0.32575129796298685,
        "rsi": 46.81314806717409,
        "dist_from_ma20": -3.1838151816867644,
        "volume_ratio": 0.7194833679477054,
        "macd": {
          "macd": 2.5327926483338956,
          "signal": 5.194466343846221,
          "histogram": -2.6616736955123255,
          "crossover": null
        },
        "bollinger": {
          "upper": 432.93110917334843,
          "lower": 401.41289107079217,
          "middle": 417.1720001220703,
          "percent_b": 0.07859338905470752
        },
        "score": 25.0,
        "signals": [
          {
            "kind": "bull",
            "label": "BB inferiore",
            "value": "%B 0.08"
          }
        ]
      },
      {
        "type": "stock",
        "symbol": "JPM",
        "name": "JPMorgan",
        "price": 302.625,
        "change_24h": 0.7910074937552041,
        "rsi": 46.67445694497381,
        "dist_from_ma20": -2.0532011732578135,
        "volume_ratio": 0.761202812409594,
        "macd": {
          "macd": -0.189901612671747,
          "signal": 1.4447129924603128,
          "histogram": -1.6346146051320598,
          "crossover": null
        },
        "bollinger": {
          "upper": 318.51178985443124,
          "lower": 299.42571014556876,
          "middle": 308.96875,
          "percent_b": 0.16762425302801576
        },
        "score": 25.0,
        "signals": [
          {
            "kind": "bull",
            "label": "BB inferiore",
            "value": "%B 0.17"
          }
        ]
      },
      {
        "type": "stock",
        "symbol": "MA",
        "name": "Mastercard",
        "price": 491.17498779296875,
        "change_24h": 0.10903577542785191,
        "rsi": 43.276365147611244,
        "dist_from_ma20": -2.4791962027723815,
        "volume_ratio": 0.6363016790593797,
        "macd": {
          "macd": -3.5976519518446253,
          "signal": -2.198957337392647,
          "histogram": -1.398694614451978,
          "crossover": null
        },
        "bollinger": {
          "upper": 522.4837990184759,
          "lower": 484.8397025684381,
          "middle": 503.66175079345703,
          "percent_b": 0.16829425652277247
        },
        "score": 25.0,
        "signals": [
          {
            "kind": "bull",
            "label": "BB inferiore",
            "value": "%B 0.17"
          }
        ]
      },
      {
        "type": "stock",
        "symbol": "MC.PA",
        "name": "LVMH",
        "price": 460.04998779296875,
        "change_24h": 1.713464560946972,
        "rsi": 47.64065843578508,
        "dist_from_ma20": -0.8486363689758823,
        "volume_ratio": 0.7259253765815775,
        "macd": {
          "macd": -4.953600815646496,
          "signal": -5.417531137622568,
          "histogram": 0.463930321976072,
          "crossover": null
        },
        "bollinger": {
          "upper": 489.69324922556893,
          "lower": 438.28186063771227,
          "middle": 463.9875549316406,
          "percent_b": 0.42341060518248863
        },
        "score": 12.0,
        "signals": [
          {
            "kind": "bull",
            "label": "MACD ripresa",
            "value": ""
          }
        ]
      }
    ]
  }
}